karrio/mappers/freightcom/__init__.py
karrio/mappers/freightcom/mapper.py
karrio/mappers/freightcom/proxy.py
karrio/mappers/freightcom/settings.py
karrio/plugins/freightcom/__init__.py
karrio/providers/freightcom/__init__.py
karrio/providers/freightcom/error.py
karrio/providers/freightcom/quote.py
karrio/providers/freightcom/shipping.py
karrio/providers/freightcom/units.py
karrio/providers/freightcom/utils.py
karrio/providers/freightcom/void_shipment.py
karrio/schemas/freightcom/__init__.py
karrio/schemas/freightcom/error.py
karrio/schemas/freightcom/quote_reply.py
karrio/schemas/freightcom/quote_request.py
karrio/schemas/freightcom/shipment_cancel_reply.py
karrio/schemas/freightcom/shipment_cancel_request.py
karrio/schemas/freightcom/shipping_reply.py
karrio/schemas/freightcom/shipping_request.py
karrio_freightcom-2026.1.4.dist-info/METADATA
karrio_freightcom-2026.1.4.dist-info/WHEEL
karrio_freightcom-2026.1.4.dist-info/entry_points.txt
karrio_freightcom-2026.1.4.dist-info/top_level.txt
karrio_freightcom-2026.1.4.dist-info/RECORD
